libjacobi-motion.so
jacobi.cpython-310-aarch64-linux-gnu.so
jacobi_scripts/create_blender.py
jacobi-stubs/License.pyi
jacobi-stubs/__init__.pyi
jacobi-stubs/drivers.pyi
jacobi-stubs/exceptions.pyi
jacobi-stubs/robots.pyi
jacobi_motion.libs/libcrypto-3eda328c.so.1.1.1k
jacobi_motion.libs/libgomp-bc9a3cf4.so.1.0.0
jacobi_motion.libs/libssl-f60bf0e2.so.1.1.1k
jacobi_motion-1.1.21.dist-info/entry_points.txt
jacobi_motion-1.1.21.dist-info/WHEEL
jacobi_motion-1.1.21.dist-info/METADATA
jacobi_motion-1.1.21.dist-info/RECORD
jacobi_motion-1.1.21.dist-info/licenses/LICENSE
