Metadata-Version: 2.2
Name: jacobi-motion
Version: 1.1.21
Summary: Next-Generation Motion Planning.
Keywords: robotics,motion-planning,trajectory-generation,obstacle-avoidance
Author-Email: Lars Berscheid <lars.berscheid@jacobirobotics.com>
License: Copyright (c) 2022-2024 Jacobi Robotics Inc.
Classifier: Development Status :: 5 - Production/Stable
Classifier: Intended Audience :: Science/Research
Classifier: Topic :: Scientific/Engineering
Classifier: License :: Other/Proprietary License
Classifier: Programming Language :: C++
Project-URL: homepage, https://www.jacobirobotics.com
Project-URL: documentation, https://docs.jacobirobotics.com
Project-URL: issues, https://issues.jacobirobotics.com
Requires-Python: >=3.10
